tina4_python/Api.py
tina4_python/Auth.py
tina4_python/CRUD.py
tina4_python/Constant.py
tina4_python/Database.py
tina4_python/DatabaseResult.py
tina4_python/DatabaseTypes.py
tina4_python/Debug.py
tina4_python/Env.py
tina4_python/FieldTypes.py
tina4_python/HtmlElement.py
tina4_python/Localization.py
tina4_python/Messages.py
tina4_python/MiddleWare.py
tina4_python/Migration.py
tina4_python/ORM.py
tina4_python/Queue.py
tina4_python/Request.py
tina4_python/Response.py
tina4_python/Router.py
tina4_python/Session.py
tina4_python/ShellColors.py
tina4_python/Swagger.py
tina4_python/Template.py
tina4_python/Testing.py
tina4_python/WSDL.py
tina4_python/Webserver.py
tina4_python/Websocket.py
tina4_python/__init__.py
tina4_python/cli.py
tina4_python/messages.pot
tina4_python/public/favicon.ico
tina4_python/public/css/readme.md
tina4_python/public/images/403.png
tina4_python/public/images/404.png
tina4_python/public/images/500.png
tina4_python/public/images/logo.png
tina4_python/public/images/readme.md
tina4_python/public/js/readme.md
tina4_python/public/js/reconnecting-websocket.js
tina4_python/public/js/tina4helper.js
tina4_python/public/swagger/index.html
tina4_python/public/swagger/oauth2-redirect.html
tina4_python/templates/readme.md
tina4_python/templates/components/crud.twig
tina4_python/templates/errors/403.twig
tina4_python/templates/errors/404.twig
tina4_python/templates/errors/500.twig
tina4_python/translations/en/LC_MESSAGES/messages.mo
tina4_python/translations/en/LC_MESSAGES/messages.po
tina4_python/translations/fr/LC_MESSAGES/messages.mo
tina4_python/translations/fr/LC_MESSAGES/messages.po
tina4_python-0.2.168.dist-info/METADATA
tina4_python-0.2.168.dist-info/WHEEL
tina4_python-0.2.168.dist-info/entry_points.txt
tina4_python-0.2.168.dist-info/RECORD
