Metadata-Version: 2.4
Name: tina4-python
Version: 0.2.168
Summary: Tina4Python - This is not another framework for Python
Author-email: Andre van Zuydam <andrevanzuydam@gmail.com>
Requires-Python: <4.0,>=3.12
Requires-Dist: asyncer>=0.0.8
Requires-Dist: bcrypt<5.0.0,>=4.2.1
Requires-Dist: cryptography<45.0.0,>=44.0.0
Requires-Dist: hypercorn>=0.18.0
Requires-Dist: jinja2<4.0.0,>=3.1.5
Requires-Dist: libsass<0.24.0,>=0.23.0
Requires-Dist: litequeue<0.10,>=0.9
Requires-Dist: pyjwt<3.0.0,>=2.10.1
Requires-Dist: python-dotenv<2.0.0,>=1.0.1
Requires-Dist: requests>=2.32.5
Requires-Dist: simple-websocket<2.0.0,>=1.1.0
Requires-Dist: watchdog<7.0.0,>=6.0.0
